yeo/__init__.py
yeo/main.py
yeo/utils/__init__.py
yeo/utils/consts.py
yeo/utils/fs_helpers.py
yeo-0.3.2a1.dist-info/licenses/LICENSE
yeo-0.3.2a1.dist-info/METADATA
yeo-0.3.2a1.dist-info/WHEEL
yeo-0.3.2a1.dist-info/entry_points.txt
yeo-0.3.2a1.dist-info/top_level.txt
yeo-0.3.2a1.dist-info/RECORD
