Metadata-Version: 2.4
Name: yeo
Version: 0.3.2a1
Summary: A declarative dotfiles snapshot tool
Requires-Python: >=3.14
License-File: LICENSE
Dynamic: license-file
